topsis/__init__.py
topsis/topsis.py
topsis102218038-0.1.0.dist-info/METADATA
topsis102218038-0.1.0.dist-info/WHEEL
topsis102218038-0.1.0.dist-info/top_level.txt
topsis102218038-0.1.0.dist-info/RECORD
